pyfy6900/__init__.py
pyfy6900/fy6900.py
pyfy6900_tspspi-0.0.1a2.dist-info/LICENSE.md
pyfy6900_tspspi-0.0.1a2.dist-info/METADATA
pyfy6900_tspspi-0.0.1a2.dist-info/WHEEL
pyfy6900_tspspi-0.0.1a2.dist-info/top_level.txt
pyfy6900_tspspi-0.0.1a2.dist-info/RECORD
