Metadata-Version: 2.1
Name: pyfy6900-tspspi
Version: 0.0.1a2
Summary: (Unofficial) control library for the FY6900 function generator
Home-page: https://github.com/tspspi/pyfy6900
Author: Thomas Spielauer
Author-email: pypipackages01@tspi.at
Classifier: Programming Language :: Python :: 3
Classifier: License :: OSI Approved :: BSD License
Classifier: Operating System :: OS Independent
Requires-Python: >=3.6
License-File: LICENSE.md
Requires-Dist: pylabdevs-tspspi>=0.0.5
Requires-Dist: pyserial>=3.5
